{
  "collections": [
    {
      "name": "Brand",
      "modes": ["light"],
      "variables": [
        {
          "name": "color/primary",
          "type": "COLOR",
          "values": {
            "light": {
              "r": 0.9803921568627451,
              "g": 0.9725490196078431,
              "b": 0.9294117647058824,
              "a": 1
            }
          }
        },
        {
          "name": "color/accent",
          "type": "COLOR",
          "values": {
            "light": {
              "r": 0.9803921568627451,
              "g": 0.9725490196078431,
              "b": 0.9294117647058824,
              "a": 1
            }
          }
        },
        {
          "name": "color/neutral/50",
          "type": "COLOR",
          "values": {
            "light": {
              "r": 0,
              "g": 0,
              "b": 0,
              "a": 1
            }
          }
        },
        {
          "name": "color/neutral/100",
          "type": "COLOR",
          "values": {
            "light": {
              "r": 0.08627450980392157,
              "g": 0.08627450980392157,
              "b": 0.08627450980392157,
              "a": 1
            }
          }
        },
        {
          "name": "color/background/default",
          "type": "COLOR",
          "values": {
            "light": {
              "r": 0.08627450980392157,
              "g": 0.08627450980392157,
              "b": 0.08627450980392157,
              "a": 1
            }
          }
        },
        {
          "name": "color/background/1",
          "type": "COLOR",
          "values": {
            "light": {
              "r": 0.9803921568627451,
              "g": 0.9725490196078431,
              "b": 0.9294117647058824,
              "a": 1
            }
          }
        },
        {
          "name": "color/text/default",
          "type": "COLOR",
          "values": {
            "light": {
              "r": 0,
              "g": 0,
              "b": 0,
              "a": 1
            }
          }
        }
      ]
    },
    {
      "name": "Typography",
      "modes": ["default"],
      "variables": [
        {
          "name": "font/size/14.5",
          "type": "FLOAT",
          "values": {
            "default": 14.5
          }
        },
        {
          "name": "font/weight/14.5",
          "type": "FLOAT",
          "values": {
            "default": 400
          }
        },
        {
          "name": "font/lineHeight/14.5",
          "type": "FLOAT",
          "values": {
            "default": 23.925
          }
        },
        {
          "name": "font/size/13.824",
          "type": "FLOAT",
          "values": {
            "default": 13.824
          }
        },
        {
          "name": "font/weight/13.824",
          "type": "FLOAT",
          "values": {
            "default": 500
          }
        },
        {
          "name": "font/lineHeight/13.824",
          "type": "FLOAT",
          "values": {
            "default": 21.4272
          }
        },
        {
          "name": "font/size/11.52",
          "type": "FLOAT",
          "values": {
            "default": 11.52
          }
        },
        {
          "name": "font/weight/11.52",
          "type": "FLOAT",
          "values": {
            "default": 400
          }
        }
      ]
    },
    {
      "name": "Spacing",
      "modes": ["default"],
      "variables": [
        {
          "name": "spacing/26",
          "type": "FLOAT",
          "values": {
            "default": 26
          }
        },
        {
          "name": "spacing/330",
          "type": "FLOAT",
          "values": {
            "default": 330
          }
        }
      ]
    }
  ]
}
