[
  {
    "slug": "bekaa-feb-2025",
    "referenceNumber": "AT-001",
    "title": "Bekaa",
    "titleItalic": "February 2025",
    "subtitle": "Bekaa, Lebanon",
    "year": 2025,
    "description": [
      "Signed and numbered by the artist. Limited edition of 10. Printed to order on archival pigment paper with a 1 inch border for handling."
    ],
    "imageUrl": "/images/catalog/bekaa-feb-2025.jpg",
    "imageAlt": "Documentary photograph: Bekaa, February 2025. Bekaa, Lebanon. Archival pigment print by Thalia Bassim.",
    "basePriceCents": 30000,
    "sizes": [
      {
        "id": "8x10",
        "label": "8 × 10 in",
        "multiplier": 1
      }
    ],
    "papers": [
      {
        "id": "photo-rag",
        "name": "Hahnemühle Photo Rag",
        "surchargeCents": 0
      },
      {
        "id": "baryta",
        "name": "Canson Baryta",
        "surchargeCents": 0
      },
      {
        "id": "bamboo",
        "name": "Hahnemühle Bamboo",
        "surchargeCents": 0
      }
    ],
    "editionTotal": 10,
    "editionSold": 2
  },
  {
    "slug": "north-lebanon-jul-2022",
    "referenceNumber": "AT-022",
    "title": "North Lebanon",
    "titleItalic": "July 2022",
    "subtitle": "North Lebanon, Lebanon",
    "year": 2022,
    "description": [
      "Signed and numbered by the artist. Limited edition of 10. Printed to order on archival pigment paper with a 1 inch border for handling."
    ],
    "imageUrl": "/images/catalog/north-lebanon-jul-2022.jpg",
    "imageAlt": "Documentary photograph: North Lebanon, July 2022. North Lebanon, Lebanon. Archival pigment print by Thalia Bassim.",
    "basePriceCents": 30000,
    "sizes": [
      {
        "id": "8x10",
        "label": "8 × 10 in",
        "multiplier": 1
      }
    ],
    "papers": [
      {
        "id": "photo-rag",
        "name": "Hahnemühle Photo Rag",
        "surchargeCents": 0
      },
      {
        "id": "baryta",
        "name": "Canson Baryta",
        "surchargeCents": 0
      },
      {
        "id": "bamboo",
        "name": "Hahnemühle Bamboo",
        "surchargeCents": 0
      }
    ],
    "editionTotal": 10,
    "editionSold": 4
  },
  {
    "slug": "mount-lebanon-mar-2023",
    "referenceNumber": "AT-011",
    "title": "Mount Lebanon",
    "titleItalic": "March 2023",
    "subtitle": "Mount Lebanon, Lebanon",
    "year": 2023,
    "description": [
      "Signed and numbered by the artist. Limited edition of 10. Printed to order on archival pigment paper with a 1 inch border for handling."
    ],
    "imageUrl": "/images/catalog/mount-lebanon-mar-2023.jpg",
    "imageAlt": "Documentary photograph: Mount Lebanon, March 2023. Mount Lebanon, Lebanon. Archival pigment print by Thalia Bassim.",
    "basePriceCents": 30000,
    "sizes": [
      {
        "id": "8x10",
        "label": "8 × 10 in",
        "multiplier": 1
      }
    ],
    "papers": [
      {
        "id": "photo-rag",
        "name": "Hahnemühle Photo Rag",
        "surchargeCents": 0
      },
      {
        "id": "baryta",
        "name": "Canson Baryta",
        "surchargeCents": 0
      },
      {
        "id": "bamboo",
        "name": "Hahnemühle Bamboo",
        "surchargeCents": 0
      }
    ],
    "editionTotal": 10,
    "editionSold": 2
  },
  {
    "slug": "keserwan-feb-2026",
    "referenceNumber": "AT-003",
    "title": "Keserwan, Lebanon",
    "titleItalic": "February 2026",
    "subtitle": "Keserwan, Lebanon",
    "year": 2026,
    "description": [
      "Signed and numbered by the artist. Limited edition of 10. Printed to order on archival pigment paper with a 1 inch border for handling."
    ],
    "imageUrl": "/images/catalog/keserwan-feb-2026.jpg",
    "imageAlt": "Documentary photograph: Keserwan, Lebanon, February 2026. Keserwan, Lebanon. Archival pigment print by Thalia Bassim.",
    "basePriceCents": 30000,
    "sizes": [
      {
        "id": "8x10",
        "label": "8 × 10 in",
        "multiplier": 1
      }
    ],
    "papers": [
      {
        "id": "photo-rag",
        "name": "Hahnemühle Photo Rag",
        "surchargeCents": 0
      },
      {
        "id": "baryta",
        "name": "Canson Baryta",
        "surchargeCents": 0
      },
      {
        "id": "bamboo",
        "name": "Hahnemühle Bamboo",
        "surchargeCents": 0
      }
    ],
    "editionTotal": 10,
    "editionSold": 2
  },
  {
    "slug": "north-lebanon-2-oct-2020",
    "referenceNumber": "AT-016",
    "title": "North Lebanon (2)",
    "titleItalic": "October 2020",
    "subtitle": "North Lebanon, Lebanon",
    "year": 2020,
    "description": [
      "Signed and numbered by the artist. Limited edition of 10. Printed to order on archival pigment paper with a 1 inch border for handling."
    ],
    "imageUrl": "/images/catalog/north-lebanon-2-oct-2020.jpg",
    "imageAlt": "Documentary photograph: North Lebanon (2), October 2020. North Lebanon, Lebanon. Archival pigment print by Thalia Bassim.",
    "basePriceCents": 30000,
    "sizes": [
      {
        "id": "8x10",
        "label": "8 × 10 in",
        "multiplier": 1
      }
    ],
    "papers": [
      {
        "id": "photo-rag",
        "name": "Hahnemühle Photo Rag",
        "surchargeCents": 0
      },
      {
        "id": "baryta",
        "name": "Canson Baryta",
        "surchargeCents": 0
      },
      {
        "id": "bamboo",
        "name": "Hahnemühle Bamboo",
        "surchargeCents": 0
      }
    ],
    "editionTotal": 10,
    "editionSold": 2
  },
  {
    "slug": "mount-lebanon-jan-2025",
    "referenceNumber": "AT-010",
    "title": "Mount Lebanon",
    "titleItalic": "January 2025",
    "subtitle": "Mount Lebanon, Lebanon",
    "year": 2025,
    "description": [
      "Signed and numbered by the artist. Limited edition of 10. Printed to order on archival pigment paper with a 1 inch border for handling."
    ],
    "imageUrl": "/images/catalog/mount-lebanon-jan-2025.jpg",
    "imageAlt": "Documentary photograph: Mount Lebanon, January 2025. Mount Lebanon, Lebanon. Archival pigment print by Thalia Bassim.",
    "basePriceCents": 30000,
    "sizes": [
      {
        "id": "8x10",
        "label": "8 × 10 in",
        "multiplier": 1
      }
    ],
    "papers": [
      {
        "id": "photo-rag",
        "name": "Hahnemühle Photo Rag",
        "surchargeCents": 0
      },
      {
        "id": "baryta",
        "name": "Canson Baryta",
        "surchargeCents": 0
      },
      {
        "id": "bamboo",
        "name": "Hahnemühle Bamboo",
        "surchargeCents": 0
      }
    ],
    "editionTotal": 10,
    "editionSold": 2
  },
  {
    "slug": "tyre-feb-2022",
    "referenceNumber": "AT-002",
    "title": "Tyre",
    "titleItalic": "February 2022",
    "subtitle": "Tyre, Lebanon",
    "year": 2022,
    "description": [
      "Signed and numbered by the artist. Limited edition of 10. Printed to order on archival pigment paper with a 1 inch border for handling."
    ],
    "imageUrl": "/images/catalog/tyre-feb-2022.jpg",
    "imageAlt": "Documentary photograph: Tyre, February 2022. Tyre, Lebanon. Archival pigment print by Thalia Bassim.",
    "basePriceCents": 30000,
    "sizes": [
      {
        "id": "8x10",
        "label": "8 × 10 in",
        "multiplier": 1
      }
    ],
    "papers": [
      {
        "id": "photo-rag",
        "name": "Hahnemühle Photo Rag",
        "surchargeCents": 0
      },
      {
        "id": "baryta",
        "name": "Canson Baryta",
        "surchargeCents": 0
      },
      {
        "id": "bamboo",
        "name": "Hahnemühle Bamboo",
        "surchargeCents": 0
      }
    ],
    "editionTotal": 10,
    "editionSold": 1
  },
  {
    "slug": "north-lebanon-feb-2026",
    "referenceNumber": "AT-024",
    "title": "North Lebanon",
    "titleItalic": "February 2026",
    "subtitle": "North Lebanon, Lebanon",
    "year": 2026,
    "description": [
      "Signed and numbered by the artist. Limited edition of 10. Printed to order on archival pigment paper with a 1 inch border for handling."
    ],
    "imageUrl": "/images/catalog/north-lebanon-feb-2026.jpg",
    "imageAlt": "Documentary photograph: North Lebanon, February 2026. North Lebanon, Lebanon. Archival pigment print by Thalia Bassim.",
    "basePriceCents": 30000,
    "sizes": [
      {
        "id": "8x10",
        "label": "8 × 10 in",
        "multiplier": 1
      }
    ],
    "papers": [
      {
        "id": "photo-rag",
        "name": "Hahnemühle Photo Rag",
        "surchargeCents": 0
      },
      {
        "id": "baryta",
        "name": "Canson Baryta",
        "surchargeCents": 0
      },
      {
        "id": "bamboo",
        "name": "Hahnemühle Bamboo",
        "surchargeCents": 0
      }
    ],
    "editionTotal": 10,
    "editionSold": 3
  },
  {
    "slug": "mount-lebanon-2-mar-2026",
    "referenceNumber": "AT-005",
    "title": "Mount Lebanon (2)",
    "titleItalic": "March 2026",
    "subtitle": "Mount Lebanon, Lebanon",
    "year": 2026,
    "description": [
      "Signed and numbered by the artist. Limited edition of 10. Printed to order on archival pigment paper with a 1 inch border for handling."
    ],
    "imageUrl": "/images/catalog/mount-lebanon-2-mar-2026.jpg",
    "imageAlt": "Documentary photograph: Mount Lebanon (2), March 2026. Mount Lebanon, Lebanon. Archival pigment print by Thalia Bassim.",
    "basePriceCents": 30000,
    "sizes": [
      {
        "id": "8x10",
        "label": "8 × 10 in",
        "multiplier": 1
      }
    ],
    "papers": [
      {
        "id": "photo-rag",
        "name": "Hahnemühle Photo Rag",
        "surchargeCents": 0
      },
      {
        "id": "baryta",
        "name": "Canson Baryta",
        "surchargeCents": 0
      },
      {
        "id": "bamboo",
        "name": "Hahnemühle Bamboo",
        "surchargeCents": 0
      }
    ],
    "editionTotal": 10,
    "editionSold": 0
  },
  {
    "slug": "north-lebanon-2-jul-2021",
    "referenceNumber": "AT-013",
    "title": "North Lebanon (2)",
    "titleItalic": "July 2021",
    "subtitle": "North Lebanon, Lebanon",
    "year": 2021,
    "description": [
      "Signed and numbered by the artist. Limited edition of 10. Printed to order on archival pigment paper with a 1 inch border for handling."
    ],
    "imageUrl": "/images/catalog/north-lebanon-2-jul-2021.jpg",
    "imageAlt": "Documentary photograph: North Lebanon (2), July 2021. North Lebanon, Lebanon. Archival pigment print by Thalia Bassim.",
    "basePriceCents": 30000,
    "sizes": [
      {
        "id": "8x10",
        "label": "8 × 10 in",
        "multiplier": 1
      }
    ],
    "papers": [
      {
        "id": "photo-rag",
        "name": "Hahnemühle Photo Rag",
        "surchargeCents": 0
      },
      {
        "id": "baryta",
        "name": "Canson Baryta",
        "surchargeCents": 0
      },
      {
        "id": "bamboo",
        "name": "Hahnemühle Bamboo",
        "surchargeCents": 0
      }
    ],
    "editionTotal": 10,
    "editionSold": 3
  },
  {
    "slug": "mount-lebanon-mar-2021",
    "referenceNumber": "AT-025",
    "title": "Mount Lebanon",
    "titleItalic": "March 2021",
    "subtitle": "Mount Lebanon, Lebanon",
    "year": 2021,
    "description": [
      "Signed and numbered by the artist. Limited edition of 10. Printed to order on archival pigment paper with a 1 inch border for handling."
    ],
    "imageUrl": "/images/catalog/mount-lebanon-mar-2021.jpg",
    "imageAlt": "Documentary photograph: Mount Lebanon, March 2021. Mount Lebanon, Lebanon. Archival pigment print by Thalia Bassim.",
    "basePriceCents": 30000,
    "sizes": [
      {
        "id": "8x10",
        "label": "8 × 10 in",
        "multiplier": 1
      }
    ],
    "papers": [
      {
        "id": "photo-rag",
        "name": "Hahnemühle Photo Rag",
        "surchargeCents": 0
      },
      {
        "id": "baryta",
        "name": "Canson Baryta",
        "surchargeCents": 0
      },
      {
        "id": "bamboo",
        "name": "Hahnemühle Bamboo",
        "surchargeCents": 0
      }
    ],
    "editionTotal": 10,
    "editionSold": 0
  },
  {
    "slug": "mount-lebanon-4-feb-2025",
    "referenceNumber": "AT-008",
    "title": "Mount Lebanon (4)",
    "titleItalic": "February 2025",
    "subtitle": "Mount Lebanon, Lebanon",
    "year": 2025,
    "description": [
      "Signed and numbered by the artist. Limited edition of 10. Printed to order on archival pigment paper with a 1 inch border for handling."
    ],
    "imageUrl": "/images/catalog/mount-lebanon-4-feb-2025.jpg",
    "imageAlt": "Documentary photograph: Mount Lebanon (4), February 2025. Mount Lebanon, Lebanon. Archival pigment print by Thalia Bassim.",
    "basePriceCents": 30000,
    "sizes": [
      {
        "id": "8x10",
        "label": "8 × 10 in",
        "multiplier": 1
      }
    ],
    "papers": [
      {
        "id": "photo-rag",
        "name": "Hahnemühle Photo Rag",
        "surchargeCents": 0
      },
      {
        "id": "baryta",
        "name": "Canson Baryta",
        "surchargeCents": 0
      },
      {
        "id": "bamboo",
        "name": "Hahnemühle Bamboo",
        "surchargeCents": 0
      }
    ],
    "editionTotal": 10,
    "editionSold": 2
  },
  {
    "slug": "north-lebanon-oct-2020",
    "referenceNumber": "AT-023",
    "title": "North Lebanon",
    "titleItalic": "October 2020",
    "subtitle": "North Lebanon, Lebanon",
    "year": 2020,
    "description": [
      "Signed and numbered by the artist. Limited edition of 10. Printed to order on archival pigment paper with a 1 inch border for handling."
    ],
    "imageUrl": "/images/catalog/north-lebanon-oct-2020.jpg",
    "imageAlt": "Documentary photograph: North Lebanon, October 2020. North Lebanon, Lebanon. Archival pigment print by Thalia Bassim.",
    "basePriceCents": 30000,
    "sizes": [
      {
        "id": "8x10",
        "label": "8 × 10 in",
        "multiplier": 1
      }
    ],
    "papers": [
      {
        "id": "photo-rag",
        "name": "Hahnemühle Photo Rag",
        "surchargeCents": 0
      },
      {
        "id": "baryta",
        "name": "Canson Baryta",
        "surchargeCents": 0
      },
      {
        "id": "bamboo",
        "name": "Hahnemühle Bamboo",
        "surchargeCents": 0
      }
    ],
    "editionTotal": 10,
    "editionSold": 2
  },
  {
    "slug": "north-lebanon-apr-2022",
    "referenceNumber": "AT-019",
    "title": "North Lebanon",
    "titleItalic": "April 2022",
    "subtitle": "North Lebanon, Lebanon",
    "year": 2022,
    "description": [
      "Signed and numbered by the artist. Limited edition of 10. Printed to order on archival pigment paper with a 1 inch border for handling."
    ],
    "imageUrl": "/images/catalog/north-lebanon-apr-2022.jpg",
    "imageAlt": "Documentary photograph: North Lebanon, April 2022. North Lebanon, Lebanon. Archival pigment print by Thalia Bassim.",
    "basePriceCents": 30000,
    "sizes": [
      {
        "id": "8x10",
        "label": "8 × 10 in",
        "multiplier": 1
      }
    ],
    "papers": [
      {
        "id": "photo-rag",
        "name": "Hahnemühle Photo Rag",
        "surchargeCents": 0
      },
      {
        "id": "baryta",
        "name": "Canson Baryta",
        "surchargeCents": 0
      },
      {
        "id": "bamboo",
        "name": "Hahnemühle Bamboo",
        "surchargeCents": 0
      }
    ],
    "editionTotal": 10,
    "editionSold": 1
  },
  {
    "slug": "mount-lebanon-3-mar-2026",
    "referenceNumber": "AT-007",
    "title": "Mount Lebanon (3)",
    "titleItalic": "March 2026",
    "subtitle": "Mount Lebanon, Lebanon",
    "year": 2026,
    "description": [
      "Signed and numbered by the artist. Limited edition of 10. Printed to order on archival pigment paper with a 1 inch border for handling."
    ],
    "imageUrl": "/images/catalog/mount-lebanon-3-mar-2026.jpg",
    "imageAlt": "Documentary photograph: Mount Lebanon (3), March 2026. Mount Lebanon, Lebanon. Archival pigment print by Thalia Bassim.",
    "basePriceCents": 30000,
    "sizes": [
      {
        "id": "8x10",
        "label": "8 × 10 in",
        "multiplier": 1
      }
    ],
    "papers": [
      {
        "id": "photo-rag",
        "name": "Hahnemühle Photo Rag",
        "surchargeCents": 0
      },
      {
        "id": "baryta",
        "name": "Canson Baryta",
        "surchargeCents": 0
      },
      {
        "id": "bamboo",
        "name": "Hahnemühle Bamboo",
        "surchargeCents": 0
      }
    ],
    "editionTotal": 10,
    "editionSold": 1
  },
  {
    "slug": "north-lebanon-jul-2021",
    "referenceNumber": "AT-021",
    "title": "North Lebanon",
    "titleItalic": "July 2021",
    "subtitle": "North Lebanon, Lebanon",
    "year": 2021,
    "description": [
      "Signed and numbered by the artist. Limited edition of 10. Printed to order on archival pigment paper with a 1 inch border for handling."
    ],
    "imageUrl": "/images/catalog/north-lebanon-jul-2021.jpg",
    "imageAlt": "Documentary photograph: North Lebanon, July 2021. North Lebanon, Lebanon. Archival pigment print by Thalia Bassim.",
    "basePriceCents": 30000,
    "sizes": [
      {
        "id": "8x10",
        "label": "8 × 10 in",
        "multiplier": 1
      }
    ],
    "papers": [
      {
        "id": "photo-rag",
        "name": "Hahnemühle Photo Rag",
        "surchargeCents": 0
      },
      {
        "id": "baryta",
        "name": "Canson Baryta",
        "surchargeCents": 0
      },
      {
        "id": "bamboo",
        "name": "Hahnemühle Bamboo",
        "surchargeCents": 0
      }
    ],
    "editionTotal": 10,
    "editionSold": 3
  },
  {
    "slug": "mount-lebanon-2-feb-2025",
    "referenceNumber": "AT-004",
    "title": "Mount Lebanon (2)",
    "titleItalic": "February 2025",
    "subtitle": "Mount Lebanon, Lebanon",
    "year": 2025,
    "description": [
      "Signed and numbered by the artist. Limited edition of 10. Printed to order on archival pigment paper with a 1 inch border for handling."
    ],
    "imageUrl": "/images/catalog/mount-lebanon-2-feb-2025.jpg",
    "imageAlt": "Documentary photograph: Mount Lebanon (2), February 2025. Mount Lebanon, Lebanon. Archival pigment print by Thalia Bassim.",
    "basePriceCents": 30000,
    "sizes": [
      {
        "id": "8x10",
        "label": "8 × 10 in",
        "multiplier": 1
      }
    ],
    "papers": [
      {
        "id": "photo-rag",
        "name": "Hahnemühle Photo Rag",
        "surchargeCents": 0
      },
      {
        "id": "baryta",
        "name": "Canson Baryta",
        "surchargeCents": 0
      },
      {
        "id": "bamboo",
        "name": "Hahnemühle Bamboo",
        "surchargeCents": 0
      }
    ],
    "editionTotal": 10,
    "editionSold": 0
  },
  {
    "slug": "north-lebanon-2-feb-2026",
    "referenceNumber": "AT-015",
    "title": "North Lebanon (2)",
    "titleItalic": "February 2026",
    "subtitle": "North Lebanon, Lebanon",
    "year": 2026,
    "description": [
      "Signed and numbered by the artist. Limited edition of 10. Printed to order on archival pigment paper with a 1 inch border for handling."
    ],
    "imageUrl": "/images/catalog/north-lebanon-2-feb-2026.jpg",
    "imageAlt": "Documentary photograph: North Lebanon (2), February 2026. North Lebanon, Lebanon. Archival pigment print by Thalia Bassim.",
    "basePriceCents": 30000,
    "sizes": [
      {
        "id": "8x10",
        "label": "8 × 10 in",
        "multiplier": 1
      }
    ],
    "papers": [
      {
        "id": "photo-rag",
        "name": "Hahnemühle Photo Rag",
        "surchargeCents": 0
      },
      {
        "id": "baryta",
        "name": "Canson Baryta",
        "surchargeCents": 0
      },
      {
        "id": "bamboo",
        "name": "Hahnemühle Bamboo",
        "surchargeCents": 0
      }
    ],
    "editionTotal": 10,
    "editionSold": 3
  },
  {
    "slug": "mount-lebanon-mar-2026",
    "referenceNumber": "AT-012",
    "title": "Mount Lebanon",
    "titleItalic": "March 2026",
    "subtitle": "Mount Lebanon, Lebanon",
    "year": 2026,
    "description": [
      "Signed and numbered by the artist. Limited edition of 10. Printed to order on archival pigment paper with a 1 inch border for handling."
    ],
    "imageUrl": "/images/catalog/mount-lebanon-mar-2026.jpg",
    "imageAlt": "Documentary photograph: Mount Lebanon, March 2026. Mount Lebanon, Lebanon. Archival pigment print by Thalia Bassim.",
    "basePriceCents": 30000,
    "sizes": [
      {
        "id": "8x10",
        "label": "8 × 10 in",
        "multiplier": 1
      }
    ],
    "papers": [
      {
        "id": "photo-rag",
        "name": "Hahnemühle Photo Rag",
        "surchargeCents": 0
      },
      {
        "id": "baryta",
        "name": "Canson Baryta",
        "surchargeCents": 0
      },
      {
        "id": "bamboo",
        "name": "Hahnemühle Bamboo",
        "surchargeCents": 0
      }
    ],
    "editionTotal": 10,
    "editionSold": 0
  },
  {
    "slug": "north-lebanon-feb-2025",
    "referenceNumber": "AT-020",
    "title": "North Lebanon",
    "titleItalic": "February 2025",
    "subtitle": "North Lebanon, Lebanon",
    "year": 2025,
    "description": [
      "Signed and numbered by the artist. Limited edition of 10. Printed to order on archival pigment paper with a 1 inch border for handling."
    ],
    "imageUrl": "/images/catalog/north-lebanon-feb-2025.jpg",
    "imageAlt": "Documentary photograph: North Lebanon, February 2025. North Lebanon, Lebanon. Archival pigment print by Thalia Bassim.",
    "basePriceCents": 30000,
    "sizes": [
      {
        "id": "8x10",
        "label": "8 × 10 in",
        "multiplier": 1
      }
    ],
    "papers": [
      {
        "id": "photo-rag",
        "name": "Hahnemühle Photo Rag",
        "surchargeCents": 0
      },
      {
        "id": "baryta",
        "name": "Canson Baryta",
        "surchargeCents": 0
      },
      {
        "id": "bamboo",
        "name": "Hahnemühle Bamboo",
        "surchargeCents": 0
      }
    ],
    "editionTotal": 10,
    "editionSold": 2
  },
  {
    "slug": "mount-lebanon-3-feb-2025",
    "referenceNumber": "AT-006",
    "title": "Mount Lebanon (3)",
    "titleItalic": "February 2025",
    "subtitle": "Mount Lebanon, Lebanon",
    "year": 2025,
    "description": [
      "Signed and numbered by the artist. Limited edition of 10. Printed to order on archival pigment paper with a 1 inch border for handling."
    ],
    "imageUrl": "/images/catalog/mount-lebanon-3-feb-2025.jpg",
    "imageAlt": "Documentary photograph: Mount Lebanon (3), February 2025. Mount Lebanon, Lebanon. Archival pigment print by Thalia Bassim.",
    "basePriceCents": 30000,
    "sizes": [
      {
        "id": "8x10",
        "label": "8 × 10 in",
        "multiplier": 1
      }
    ],
    "papers": [
      {
        "id": "photo-rag",
        "name": "Hahnemühle Photo Rag",
        "surchargeCents": 0
      },
      {
        "id": "baryta",
        "name": "Canson Baryta",
        "surchargeCents": 0
      },
      {
        "id": "bamboo",
        "name": "Hahnemühle Bamboo",
        "surchargeCents": 0
      }
    ],
    "editionTotal": 10,
    "editionSold": 1
  },
  {
    "slug": "north-lebanon-3-feb-2026",
    "referenceNumber": "AT-017",
    "title": "North Lebanon (3)",
    "titleItalic": "February 2026",
    "subtitle": "North Lebanon, Lebanon",
    "year": 2026,
    "description": [
      "Signed and numbered by the artist. Limited edition of 10. Printed to order on archival pigment paper with a 1 inch border for handling."
    ],
    "imageUrl": "/images/catalog/north-lebanon-3-feb-2026.jpg",
    "imageAlt": "Documentary photograph: North Lebanon (3), February 2026. North Lebanon, Lebanon. Archival pigment print by Thalia Bassim.",
    "basePriceCents": 30000,
    "sizes": [
      {
        "id": "8x10",
        "label": "8 × 10 in",
        "multiplier": 1
      }
    ],
    "papers": [
      {
        "id": "photo-rag",
        "name": "Hahnemühle Photo Rag",
        "surchargeCents": 0
      },
      {
        "id": "baryta",
        "name": "Canson Baryta",
        "surchargeCents": 0
      },
      {
        "id": "bamboo",
        "name": "Hahnemühle Bamboo",
        "surchargeCents": 0
      }
    ],
    "editionTotal": 10,
    "editionSold": 4
  },
  {
    "slug": "mount-lebanon-feb-2025",
    "referenceNumber": "AT-009",
    "title": "Mount Lebanon",
    "titleItalic": "February 2025",
    "subtitle": "Mount Lebanon, Lebanon",
    "year": 2025,
    "description": [
      "Signed and numbered by the artist. Limited edition of 10. Printed to order on archival pigment paper with a 1 inch border for handling."
    ],
    "imageUrl": "/images/catalog/mount-lebanon-feb-2025.jpg",
    "imageAlt": "Documentary photograph: Mount Lebanon, February 2025. Mount Lebanon, Lebanon. Archival pigment print by Thalia Bassim.",
    "basePriceCents": 30000,
    "sizes": [
      {
        "id": "8x10",
        "label": "8 × 10 in",
        "multiplier": 1
      }
    ],
    "papers": [
      {
        "id": "photo-rag",
        "name": "Hahnemühle Photo Rag",
        "surchargeCents": 0
      },
      {
        "id": "baryta",
        "name": "Canson Baryta",
        "surchargeCents": 0
      },
      {
        "id": "bamboo",
        "name": "Hahnemühle Bamboo",
        "surchargeCents": 0
      }
    ],
    "editionTotal": 10,
    "editionSold": 0
  },
  {
    "slug": "north-lebanon-2-feb-2025",
    "referenceNumber": "AT-014",
    "title": "North Lebanon (2)",
    "titleItalic": "February 2025",
    "subtitle": "North Lebanon, Lebanon",
    "year": 2025,
    "description": [
      "Signed and numbered by the artist. Limited edition of 10. Printed to order on archival pigment paper with a 1 inch border for handling."
    ],
    "imageUrl": "/images/catalog/north-lebanon-2-feb-2025.jpg",
    "imageAlt": "Documentary photograph: North Lebanon (2), February 2025. North Lebanon, Lebanon. Archival pigment print by Thalia Bassim.",
    "basePriceCents": 30000,
    "sizes": [
      {
        "id": "8x10",
        "label": "8 × 10 in",
        "multiplier": 1
      }
    ],
    "papers": [
      {
        "id": "photo-rag",
        "name": "Hahnemühle Photo Rag",
        "surchargeCents": 0
      },
      {
        "id": "baryta",
        "name": "Canson Baryta",
        "surchargeCents": 0
      },
      {
        "id": "bamboo",
        "name": "Hahnemühle Bamboo",
        "surchargeCents": 0
      }
    ],
    "editionTotal": 10,
    "editionSold": 2
  },
  {
    "slug": "north-lebanon-3-mar-2026",
    "referenceNumber": "AT-018",
    "title": "North Lebanon (3)",
    "titleItalic": "March 2026",
    "subtitle": "North Lebanon, Lebanon",
    "year": 2026,
    "description": [
      "Signed and numbered by the artist. Limited edition of 10. Printed to order on archival pigment paper with a 1 inch border for handling."
    ],
    "imageUrl": "/images/catalog/north-lebanon-3-mar-2026.jpg",
    "imageAlt": "Documentary photograph: North Lebanon (3), March 2026. North Lebanon, Lebanon. Archival pigment print by Thalia Bassim.",
    "basePriceCents": 30000,
    "sizes": [
      {
        "id": "8x10",
        "label": "8 × 10 in",
        "multiplier": 1
      }
    ],
    "papers": [
      {
        "id": "photo-rag",
        "name": "Hahnemühle Photo Rag",
        "surchargeCents": 0
      },
      {
        "id": "baryta",
        "name": "Canson Baryta",
        "surchargeCents": 0
      },
      {
        "id": "bamboo",
        "name": "Hahnemühle Bamboo",
        "surchargeCents": 0
      }
    ],
    "editionTotal": 10,
    "editionSold": 3
  }
]
